younotyou/__init__.py
younotyou/py.typed
younotyou/younotyou.py
younotyou-0.1.1.dist-info/METADATA
younotyou-0.1.1.dist-info/WHEEL
younotyou-0.1.1.dist-info/licenses/LICENSE.txt
younotyou-0.1.1.dist-info/RECORD
