Metadata-Version: 2.1
Name: younotyou
Version: 0.1.1
Summary: Filter a list of strings and/or paths based on include and exclude patterns.
Project-URL: Homepage, https://github.com/matt-manes/younotyou
Project-URL: Documentation, https://github.com/matt-manes/younotyou/tree/main/docs
Project-URL: Source code, https://github.com/matt-manes/younotyou/tree/main/src/younotyou
Author-email: Matt Manes <mattmanes@pm.me>
License-File: LICENSE.txt
Keywords: filter,filtering,fnmatch,match,path,patternmatching,string
Classifier: License :: OSI Approved :: MIT License
Classifier: Operating System :: OS Independent
Classifier: Programming Language :: Python :: 3
Requires-Python: >=3.10
